weblate_language_data/__init__.py
weblate_language_data/admin.py
weblate_language_data/aliases.py
weblate_language_data/ambiguous.py
weblate_language_data/apps.py
weblate_language_data/case_insensitive.py
weblate_language_data/check_languages.py
weblate_language_data/countries.py
weblate_language_data/country_codes.py
weblate_language_data/docs.py
weblate_language_data/language_codes.py
weblate_language_data/languages.py
weblate_language_data/models.py
weblate_language_data/plural_tags.py
weblate_language_data/plurals.py
weblate_language_data/population.py
weblate_language_data/py.typed
weblate_language_data/rtl.py
weblate_language_data/tests.py
weblate_language_data/utils.py
weblate_language_data/views.py
weblate_language_data/locale/django.pot
weblate_language_data/locale/ab/LC_MESSAGES/django.mo
weblate_language_data/locale/ab/LC_MESSAGES/django.po
weblate_language_data/locale/af/LC_MESSAGES/django.mo
weblate_language_data/locale/af/LC_MESSAGES/django.po
weblate_language_data/locale/afh/LC_MESSAGES/django.mo
weblate_language_data/locale/afh/LC_MESSAGES/django.po
weblate_language_data/locale/ang/LC_MESSAGES/django.mo
weblate_language_data/locale/ang/LC_MESSAGES/django.po
weblate_language_data/locale/ar/LC_MESSAGES/django.mo
weblate_language_data/locale/ar/LC_MESSAGES/django.po
weblate_language_data/locale/ar_LY/LC_MESSAGES/django.mo
weblate_language_data/locale/ar_LY/LC_MESSAGES/django.po
weblate_language_data/locale/ars/LC_MESSAGES/django.mo
weblate_language_data/locale/ars/LC_MESSAGES/django.po
weblate_language_data/locale/ast/LC_MESSAGES/django.mo
weblate_language_data/locale/ast/LC_MESSAGES/django.po
weblate_language_data/locale/awa/LC_MESSAGES/django.mo
weblate_language_data/locale/awa/LC_MESSAGES/django.po
weblate_language_data/locale/az/LC_MESSAGES/django.mo
weblate_language_data/locale/az/LC_MESSAGES/django.po
weblate_language_data/locale/ba/LC_MESSAGES/django.mo
weblate_language_data/locale/ba/LC_MESSAGES/django.po
weblate_language_data-2025.10.dist-info/licenses/LICENSE
weblate_language_data-2025.10.dist-info/METADATA
weblate_language_data-2025.10.dist-info/WHEEL
weblate_language_data-2025.10.dist-info/top_level.txt
weblate_language_data-2025.10.dist-info/RECORD
