Metadata-Version: 2.4
Name: weblate-language-data
Version: 2025.10
Summary: Language definitions for Weblate
Author-email: Michal Čihař <michal@weblate.org>
License-Expression: MIT
Project-URL: Documentation, https://docs.weblate.org/
Project-URL: Download, https://github.com/WeblateOrg/language-data
Project-URL: Funding, https://weblate.org/donate/
Project-URL: Homepage, https://weblate.org/
Project-URL: Issue Tracker, https://github.com/WeblateOrg/language-data/issues
Project-URL: Source Code, https://github.com/WeblateOrg/language-data
Project-URL: Twitter, https://twitter.com/WeblateOrg
Keywords: i18n l10n gettext git mercurial translate
Platform: any
Classifier: Development Status :: 5 - Production/Stable
Classifier: Intended Audience :: Developers
Classifier: Operating System :: OS Independent
Classifier: Programming Language :: Python :: 3 :: Only
Classifier: Programming Language :: Python :: 3
Classifier: Programming Language :: Python :: 3.11
Classifier: Programming Language :: Python :: 3.12
Classifier: Programming Language :: Python :: 3.13
Classifier: Programming Language :: Python :: 3.14
Classifier: Programming Language :: Python :: 3.9
Classifier: Programming Language :: Python :: 3.9
Classifier: Programming Language :: Python
Classifier: Topic :: Software Development :: Internationalization
Classifier: Topic :: Software Development :: Localization
Classifier: Topic :: Utilities
Requires-Python: >=3.9
License-File: LICENSE
Provides-Extra: dev
Requires-Dist: translate-toolkit==3.17.5; extra == "dev"
Requires-Dist: weblate-language-data[lint,test,types]; extra == "dev"
Provides-Extra: django
Requires-Dist: Django; extra == "django"
Provides-Extra: lint
Requires-Dist: pre-commit==4.5.1; extra == "lint"
Provides-Extra: test
Provides-Extra: types
Requires-Dist: django-stubs==5.2.8; extra == "types"
Requires-Dist: mypy==1.19.1; extra == "types"
Dynamic: license-file
